onnx2c/__init__.py
onnx2c/__main__.py
onnx2c/cli.py
onnx2c/compiler.py
onnx2c/dtypes.py
onnx2c/errors.py
onnx2c/onnx_import.py
onnx2c/ops.py
onnx2c/validation.py
onnx2c/codegen/__init__.py
onnx2c/codegen/c_emitter.py
onnx2c/ir/__init__.py
onnx2c/ir/model.py
onnx2c/lowering/__init__.py
onnx2c/lowering/arg_reduce.py
onnx2c/lowering/attention.py
onnx2c/lowering/average_pool.py
onnx2c/lowering/batch_normalization.py
onnx2c/lowering/cast.py
onnx2c/lowering/common.py
onnx2c/lowering/concat.py
onnx2c/lowering/constant_of_shape.py
onnx2c/lowering/conv.py
onnx2c/lowering/dropout.py
onnx2c/lowering/elementwise.py
onnx2c/lowering/expand.py
onnx2c/lowering/flatten.py
onnx2c/lowering/gather.py
onnx2c/lowering/gather_elements.py
onnx2c/lowering/gemm.py
onnx2c/lowering/logsoftmax.py
onnx2c/lowering/lrn.py
onnx2c/lowering/lstm.py
onnx2c/lowering/matmul.py
onnx2c/lowering/maxpool.py
onnx2c/lowering/negative_log_likelihood_loss.py
onnx2c/lowering/range.py
onnx2c/lowering/reduce.py
onnx2c/lowering/registry.py
onnx2c/lowering/reshape.py
onnx2c/lowering/resize.py
onnx2c/lowering/shape.py
onnx2c/lowering/size.py
onnx2c/lowering/slice.py
onnx2c/lowering/softmax.py
onnx2c/lowering/softmax_cross_entropy_loss.py
onnx2c/lowering/split.py
onnx2c/lowering/squeeze.py
onnx2c/lowering/transpose.py
onnx2c/lowering/unsqueeze.py
onnx2c/lowering/where.py
onnx2c/runtime/__init__.py
onnx2c/runtime/evaluator.py
shared/__init__.py
shared/scalar_functions.py
shared/scalar_types.py
emx_onnx2c-0.1.1.dist-info/METADATA
emx_onnx2c-0.1.1.dist-info/WHEEL
emx_onnx2c-0.1.1.dist-info/entry_points.txt
emx_onnx2c-0.1.1.dist-info/top_level.txt
emx_onnx2c-0.1.1.dist-info/RECORD
