Metadata-Version: 2.4
Name: emx-onnx2c
Version: 0.1.1
Summary: emmtrix ONNX to C Compiler
Requires-Python: >=3.10
